geesc_helpers/__init__.py
geesc_helpers/dropbox_helpers.py
geesc_helpers-0.1.3.dist-info/WHEEL
geesc_helpers-0.1.3.dist-info/METADATA
geesc_helpers-0.1.3.dist-info/RECORD
