Metadata-Version: 2.4
Name: geesc_helpers
Version: 0.1.3
Summary: Projeto python, com funções helpers pra baixar os arquivos do dropbox pela api
Requires-Python: >=3.13
Project-URL: Homepage, https://github.com/geesccedeplar/geesc_helpers
